[
  {
    "Id": 1,
    "Model": "sq5",
    "Brand": "audi",
    "Year": 2018,
    "Price": 52000,
    "Color": "dark blue",
    "Img": "C:/Users/Angelina/Documents/Audi/UUWXE7258.JPG",
    "Ratings": null,
    "Images": null
  },
  {
    "Id": 2,
    "Model": "sq5",
    "Brand": "audi",
    "Year": 2018,
    "Price": 52000,
    "Color": "dark blue",
    "Img": "C:/Users/Angelina/Documents/Audi/UUWXE7258.JPG",
    "Ratings": null,
    "Images": null
  },
    
  {
    "Id": 3,
    "Model": "sq5",
    "Brand": "audi",
    "Year": 2018,
    "Price": 52000,
    "Color": "dark blue",
    "Img": "C:/Users/Angelina/Documents/Audi/UUWXE7258.JPG",
    "Ratings": null,
    "Images": null
  }
]